numstranslate/__init__.py
numstranslate/alg.py
numstranslate-1.0.0.dist-info/METADATA
numstranslate-1.0.0.dist-info/WHEEL
numstranslate-1.0.0.dist-info/top_level.txt
numstranslate-1.0.0.dist-info/RECORD
