Metadata-Version: 2.1
Name: numstranslate
Version: 1.0.0
Summary: Dou API wrapper
Home-page: https://github.com/Xalion67/py/blob/master/number_translator.py
Author: Xalion
Author-email: xaligineer@gmail.com
License: MIT
Platform: UNKNOWN
